{
  "movies": [
    {
      "title": "Star Wars Episode IV",
      "rating": "4",
      "id": 1
    },
    {
      "title": "Adding a Movie",
      "rating": "1",
      "id": 4
    },
    {
      "title": "Another Movie",
      "rating": "1",
      "id": 5
    },
    {
      "title": "Movies Movies Movies",
      "rating": "1",
      "id": 6
    },
    {
      "title": "Too many movies",
      "rating": "1",
      "id": 7
    },
    {
      "title": "So Many",
      "rating": "1",
      "id": 8
    },
    {
      "title": "Hey Hey Hey",
      "rating": "1",
      "id": 9
    },
    {
      "title": "all the things",
      "rating": "1",
      "id": 10
    },
    {
      "title": "too many",
      "rating": "1",
      "id": 11
    },
    {
      "title": "batman",
      "rating": "1",
      "id": 12
    }
  ]
}